fppull/__init__.py
fppull/_version.py
fppull/aggregate_season.py
fppull/audit_scoring_table.py
fppull/build_player_week_wide.py
fppull/compute_points.py
fppull/compute_points_dynamic.py
fppull/export_official_scores.py
fppull/export_workbook.py
fppull/fetch_espn_idp_scores.py
fppull/fetch_espn_scoring.py
fppull/fetch_espn_team_scores.py
fppull/fetch_summaries.py
fppull/join_league_points.py
fppull/join_public_private.py
fppull/join_reports.py
fppull/league_analysis.py
fppull/league_context.py
fppull/parse_summaries.py
fppull/private_league.py
fppull/probe_matchupscore.py
fppull/public_pull.py
fppull/qc_coverage_report.py
fppull/qc_official_parity.py
fppull/qc_player_breakdown.py
fppull/qc_team_week_breakdown.py
fppull/qc_week_check.py
fppull/validate_join_analysis.py
fppull/cli/pull_range.py
fppull/cli/pull_week.py
fppull/cli/report_top.py
fppull-1.0.6.dist-info/METADATA
fppull-1.0.6.dist-info/WHEEL
fppull-1.0.6.dist-info/top_level.txt
fppull-1.0.6.dist-info/RECORD
