Metadata-Version: 2.4
Name: fppull
Version: 1.0.6
Summary: Fantasy public pull utilities
Author: Masen Lamb
Project-URL: Homepage, https://github.com/Masen222/fantasy-public-pull
Requires-Python: >=3.11
